libxr/ConfigCubemxProject.py
libxr/GeneratorCode.py
libxr/GeneratorCodeSTM32.py
libxr/GeneratorSTM32CMake.py
libxr/PackageInfo.py
libxr/PeripheralAnalyzer.py
libxr/PeripheralAnalyzerSTM32.py
libxr/STM32FlashGenerator.py
libxr/STM32ToolchainSwitch.py
libxr/__init__.py
libxr/libxr_version.py
libxr-5.1.7.dist-info/LICENSE
libxr-5.1.7.dist-info/METADATA
libxr-5.1.7.dist-info/WHEEL
libxr-5.1.7.dist-info/entry_points.txt
libxr-5.1.7.dist-info/top_level.txt
libxr-5.1.7.dist-info/RECORD
