Metadata-Version: 2.1
Name: libxr
Version: 5.1.7
Summary: C++ code generator for LibXR-based embedded systems, supporting STM32 and modular robotics applications.
Author-email: Xiao <2592509183@qq.com>
Maintainer-email: Xiao <2592509183@qq.com>
License: Apache-2.0
Project-URL: Homepage, https://github.com/Jiu-xiao/libxr
Project-URL: Documentation, https://xrobot-org.github.io/
Project-URL: Repository, https://github.com/Jiu-xiao/LibXR_CppCodeGenerator
Project-URL: Bug Tracker, https://github.com/Jiu-xiao/LibXR_CppCodeGenerator/issues
Keywords: code generation,embedded systems,automation
Requires-Python: >=3.8
License-File: LICENSE
Requires-Dist: argparse
Requires-Dist: pyyaml
Requires-Dist: requests
Requires-Dist: packaging
